{"Money":100,"Key":0,"ItemDic":{"7":{"ID":7,"Amount":23},"8":{"ID":8,"Amount":1},"14":{"ID":14,"Amount":4},"11":{"ID":11,"Amount":5},"10":{"ID":10,"Amount":4},"25":{"ID":25,"Amount":4},"9":{"ID":9,"Amount":2},"26":{"ID":26,"Amount":3},"12":{"ID":12,"Amount":1}},"ConsumablesDic":{},"FoodList":[{"Name":"烤香菇","Comment":"烤熟的走路菇\nHP+300 ","HP":300,"STR":0,"CON":0,"INT":0,"MEN":0,"SEN":0,"AGI":0,"MOV":0,"Time":3,"Price":1},{"Name":"烤香菇","Comment":"烤熟的走路菇\nHP+300 ","HP":300,"STR":0,"CON":0,"INT":0,"MEN":0,"SEN":0,"AGI":0,"MOV":0,"Time":3,"Price":1},{"Name":"烤香菇","Comment":"烤熟的走路菇\nHP+300 ","HP":300,"STR":0,"CON":0,"INT":0,"MEN":0,"SEN":0,"AGI":0,"MOV":0,"Time":3,"Price":1}],"EquipList":[{"Category":1,"ID":21,"Name":"木刀","Comment":"普通的木刀，可以用來打人","ATK":50,"DEF":0,"MTK":0,"MEF":0,"HP":0,"STR":0,"CON":0,"INT":0,"MEN":0,"DEX":0,"AGI":0,"MOV":0,"Price":10}]}